README.txt
setup.py
homie/__init__.py
homie/helpers.py
homie/main.py
homie/mqtt.py
homie/networkinformation.py
homie/node.py
homie/timer.py
homie.egg-info/PKG-INFO
homie.egg-info/SOURCES.txt
homie.egg-info/dependency_links.txt
homie.egg-info/requires.txt
homie.egg-info/top_level.txt