Metadata-Version: 1.1
Name: homie
Version: 0.4.0
Summary: Implementation of the Homie IoT convention
Home-page: https://github.com/jalmeroth/homie-python
Author: Jan Almeroth
Author-email: homie-python@almeroth.com
License: UNKNOWN
Download-URL: https://github.com/jalmeroth/homie-python/tarball/0.4.0
Platform: UNKNOWN
Classifier: Development Status :: 4 - Beta
Classifier: Intended Audience :: Developers
Classifier: Programming Language :: Python
Classifier: Programming Language :: Python :: 3
Classifier: Operating System :: OS Independent
Classifier: Topic :: Home Automation
